agntcy_app_sdk/__init__.py
agntcy_app_sdk/app_sessions.py
agntcy_app_sdk/factory.py
agntcy_app_sdk/common/__init__.py
agntcy_app_sdk/common/auth.py
agntcy_app_sdk/common/logging_config.py
agntcy_app_sdk/directory/base.py
agntcy_app_sdk/identity/base.py
agntcy_app_sdk/semantic/__init__.py
agntcy_app_sdk/semantic/base.py
agntcy_app_sdk/semantic/message.py
agntcy_app_sdk/semantic/a2a/experimental.py
agntcy_app_sdk/semantic/a2a/protocol.py
agntcy_app_sdk/semantic/a2a/utils.py
agntcy_app_sdk/semantic/acp/protocol.py
agntcy_app_sdk/semantic/ap/protocol.py
agntcy_app_sdk/semantic/fast_mcp/client.py
agntcy_app_sdk/semantic/fast_mcp/protocol.py
agntcy_app_sdk/semantic/mcp/protocol.py
agntcy_app_sdk/transport/__init__.py
agntcy_app_sdk/transport/base.py
agntcy_app_sdk/transport/nats/transport.py
agntcy_app_sdk/transport/slim/common.py
agntcy_app_sdk/transport/slim/session_manager.py
agntcy_app_sdk/transport/slim/transport.py
agntcy_app_sdk/transport/streamable_http/models.py
agntcy_app_sdk/transport/streamable_http/transport.py
agntcy_app_sdk-0.4.3.dist-info/METADATA
agntcy_app_sdk-0.4.3.dist-info/WHEEL
agntcy_app_sdk-0.4.3.dist-info/licenses/LICENSE
agntcy_app_sdk-0.4.3.dist-info/RECORD
