Metadata-Version: 2.4
Name: agntcy-app-sdk
Version: 0.4.3
Summary: Agntcy Application SDK for Python
Project-URL: Homepage, https://github.com/agntcy/app-sdk
Project-URL: Bug Tracker, https://github.com/agntcy/app-sdk/issues
Author-email: Cody Hartsook <codyhartsook@gmail.com>
License-Expression: Apache-2.0
License-File: LICENSE
Requires-Python: <4.0,>=3.12
Requires-Dist: a2a-sdk==0.3.0
Requires-Dist: agntcy-identity-service-sdk==0.0.7
Requires-Dist: asgi-lifespan>=2.1.0
Requires-Dist: coloredlogs<16,>=15.0.1
Requires-Dist: httpx>=0.28.1
Requires-Dist: ioa-observe-sdk==1.0.24
Requires-Dist: langchain-community>=0.3.24
Requires-Dist: mcp[cli]>=1.10.1
Requires-Dist: nats-py<3,>=2.10.0
Requires-Dist: slim-bindings==0.6.3
Requires-Dist: uvicorn>=0.34.3
